{"dependencies":[{"name":"_css_loader"}],"generated":{"css":"json-viewer {\n    white-space-collapse: discard;\n    display: block;\n    background-color: #23241f;\n    color: #f8f8f2;\n    padding: 0.5em;\n    font-family: monospace;\n    font-size: 13px;\n}\n\njson-viewer ul,\njson-viewer li {\n    list-style: none;\n    position: relative;\n}\n\njson-viewer ul:before {\n    content: '';\n    border-left: 1px solid #333;\n    position: absolute;\n    left: 0.5em;\n    top: 0.5em;\n    bottom: 0.5em;\n}\n\njson-viewer ul {\n    padding-left: 1.2em;\n    clear: both;\n}\n\njson-viewer ul.hover:before {\n    border-left: 1px solid #666;\n}\n\n.collapsed ul {\n    display: none;\n}\n\n.key { \n    color: #f9857b;\n    display: inline-block;\n}\n.key:hover { \n    text-decoration: underline;\n    cursor: pointer;\n}\n\n.string {\n    color: #a3eea0;\n}\n\n.number {\n    color: #d19a66;\n}\n\n.boolean {\n    color: #4ba7ef;\n}\n\n.bracket {\n}\n\n.collapsed {\n    font-size: 10px;\n    background-color: #66d9ef;\n    color: #fff;\n    padding: 0.3em;\n    border-radius: 2px;\n}","js":"\n        var reloadCSS = require('_css_loader');\n        module.hot.dispose(reloadCSS);\n        module.hot.accept(reloadCSS);\n      "},"hash":"8f1f125da4fa9261e877314d668acffb","cacheData":{}}